{
    "basic_info": {
      "description_header": "Hi",
      "description": "👋 I'm Mohammad Lebzo. A software engineering / web development student at ASAC, I'm passionate about video games, making and playing them, and I'm looking for my place in the tech industry, to expand my knowlage and sharpen my skills.",
      "section_name": {
        "about": "About me",
        "projects": "Projects",
        "skills": "Skills",
        "experience": "Experience"
      }
    },
    "projects": [
      {
        "title": "Project PlaceHolder",
        "startDate": "2021",
        "description": "One of the first apps I was working on my internship. I had to develop front-end implementation for app that shows 3D models of known buildings. This was also my first project in Angular framework. I've learned a lot!",
        "images": [
          "images/portfolio/adventure/p1.jpg",
          "images/portfolio/adventure/p2.jpg"
        ],
        "url": "https://github.com",
        "technologies": [
          {
            "class": "devicon-angularjs-plain",
            "name": "Angular"
          },
          {
            "class": "devicon-typescript-plain",
            "name": "TypeScript"
          },
          {
            "class": "devicon-csharp-plain",
            "name": "C#"
          }
        ]
      },
      {
        "title": "Ask The Lads",
        "startDate": "2021",
        "description": "It's a reviews website",
        "images": [
          "images/portfolio/projects/AskTheLads1.PNG",
          "images/portfolio/projects/AskTheLads2.PNG"
        ],
        "url": "https://404inc.github.io/ask-the-lads/index.html",
        "technologies": [
          {
            "class": "devicon-html5-plain colored",
            "name": "HTML5"
          },
          {
            "class": "devicon-codepen-plain colored",
            "name": "Codepen"
          },
          {
            "class": "devicon-javascript-plain",
            "name": "JavaScript"
          },
          {
            "class": "devicon-css3-plain colored",
            "name": "css3"
          }
        ]
      },
      {
        "title": "Project Code: V Remake",
        "startDate": "2020",
        "description": "It's a personal attempt to remake Resident Evil Code Veronica. The build shown in the link is an old build the project is still a work in progress to this day.",
        "images": [
          "images/portfolio/projects/Project_Code_V_Remake.PNG",
          "images/portfolio/projects/PCV_img2.PNG"
        ],
        "url": "https://youtu.be/DONtXI98j_c",
        "technologies": [
          {
            "class": "devicon-unity-original colored",
            "name": "Unity"
          },
          {
            "class": "",
            "name": "Blender"
          },
          {
            "class": "devicon-csharp-plain",
            "name": "C#"
          }
        ]
      }
    ],
    "experience": [
      {
        "company": "Personal Project",
        "title": "Project Manager / Game Developer / Game Designer",
        "years": "08.2020 - present",
        "mainTech": [
          "Unity"
        ],
        "technologies": [
          "C#",
          "Blender",
          "Photoshop"
        ]
      },
      {
        "company": "Asac-Code Fellows Program",
        "title": "Web Developer: JS Code Manager",
        "years": "08.2021 - 9.2021",
        "mainTech": [
          "HTML5"
        ],
        "technologies": [
          "css3",
          "JavaScript"
        ]
      }
    ]
  }
